<?xml version="1.0" encoding="UTF-8"?><response version="0.92"><file><name>Zentralbibliothek Zürich - Die Eiserne Thurbrücke Ansicht von Osten gegen Andelfingen - 000010346.jpg</name><title>File:Zentralbibliothek_Zürich_-_Die_Eiserne_Thurbrücke_Ansicht_von_Osten_gegen_Andelfingen_-_000010346.jpg</title><urls><file>http://upload.wikimedia.org/wikipedia/commons/a/a8/Zentralbibliothek_Z%C3%BCrich_-_Die_Eiserne_Thurbr%C3%BCcke_Ansicht_von_Osten_gegen_Andelfingen_-_000010346.jpg</file><description>http://commons.wikimedia.org/wiki/File:Zentralbibliothek_Zürich_-_Die_Eiserne_Thurbrücke_Ansicht_von_Osten_gegen_Andelfingen_-_000010346.jpg</description></urls><size>12674459</size><width>8580</width><height>5907</height><uploader>Beat Estermann</uploader><upload_date>2013-03-24T19:48:36Z</upload_date><sha1>9f0e6f3d71c85fdd23901242b58ad3ff3eb61ebc</sha1><date>&lt;span style="white-space:nowrap"&gt;&lt;time class="dtstart" datetime="1857"&gt;1857&lt;/time&gt;&lt;/span&gt;</date><author>&lt;span class="fn value"&gt;Eggli, Jakob, Künstler, 1812-1880&lt;/span&gt;</author><source>&lt;a rel="nofollow" class="external text" href="http://www.recherche-portal.ch/zbz/action/search.do?vid=ZAD&amp;amp;fn=search&amp;amp;vl%28freeText0%29=ebi01_prod006736881"&gt;Zentralbibliothek Zürich&lt;/a&gt;</source><permission>Public domain</permission></file><meta><item name="Software">Adobe Photoshop CS6 (Windows)</item><item name="DateTimeDigitized">2010:02:22 10:12:19</item><item name="DateTime">2013:02:25 16:51:27</item><item name="DateTimeMetadata">2013:02:25 16:51:27</item><item name="OriginalDocumentID">xmp.did:2417587B871FDF11B845EB1F0615296E</item><item name="MEDIAWIKI_EXIF_VERSION">1</item></meta><description><language code="default">&lt;div class="description"&gt;
&lt;div class="description mw-content-ltr de" dir="ltr" lang="de" style=""&gt;&lt;span class="language de" title="Deutsch"&gt;&lt;b&gt;Deutsch:&lt;/b&gt;&lt;/span&gt; Die Eiserne Thurbrücke, Ansicht von Osten gegen Andelfingen&lt;/div&gt;
&lt;div class="description mw-content-ltr en" dir="ltr" lang="en" style=""&gt;&lt;span class="language en" title=""&gt;&lt;b&gt;English:&lt;/b&gt;&lt;/span&gt; The Iron Thur Bridge, view from east from Regensdorf&lt;/div&gt;
&lt;div class="description mw-content-ltr fr" dir="ltr" lang="fr" style=""&gt;&lt;span class="language fr" title="Français"&gt;&lt;b&gt;Français&amp;#160;:&lt;/b&gt;&lt;/span&gt; Pont de fer du Thur, vue de l'est à Regensdorf&lt;/div&gt;
&lt;/div&gt;</language></description><categories><category>1857 lithographs</category><category>Artworks without Wikidata item</category><category>Author died more than 100 years ago public domain images</category><category>History of rail transport in Switzerland</category><category>Media contributed by Zentralbibliothek Zürich</category><category>Rivers of Switzerland in art</category><category>Supported by Wikimedia CH</category><category>Thurbrücke Andelfingen</category></categories><licenses><license><name>CC-PD-Mark</name></license></licenses></response>